CPU_MIPS/new.v
`timescale 1ns/10ps
module tb();

    reg CLK, RESET;
    wire [31:0] DATA;

    localparam PER = 20.0;
    localparam HPER = PER / 2;

    top top(
       .clk	(CLK    ),
       .reset	(RESET	),
       .data	(DATA	)
   ); 

    initial begin
	CLK = 0;
	RESET = 1;
	#(PER*5) RESET = 0;
    end

    always #(HPER) CLK <= ~CLK;

    initial begin
	$dumpfile("tb.vcd");
	$dumpvars(0, tb);
	#(PER*500) $finish;
    end
endmodule

module top(
    input clk, reset,
    output [31:0] data
);

    wire [31:0] instr;
    wire [5:0] addr;

    imem imem(
	.addr	(addr	),
	.instr	(instr	)
    );

    mips mips(
	.clk	(clk	),
	.reset	(reset	),
	.instr	(instr	),
	.addr	(addr	),
	.data	(data	)
    );

endmodule

module imem(
    input [5:0] addr,
    output [31:0] instr
);

    reg [31:0] ram[0:63];
    
    initial
	$readmemh("memfile.dat", ram);

    assign instr = ram[addr/4];


endmodule

module mips(
    input clk, reset,
    input [31:0] instr,
    output [31:0] data,
    output [5:0] addr	// pc addr
);

    wire [2:0] control;
    wire [31:0] b;
    
    // pc set
    reg [31:0] pc;

    always @(posedge clk) begin
	if(reset)
	    pc <= 0;
	else
	    pc <= pc + 4;
    end    

    assign addr = pc[5:0];

    // connect to regfile
    wire regwrite;
    wire [31:0] rd1, rd2;
    wire [31:0] writedata;

    // DUT SET
    regfile register(
	.rs	(instr[25:21]	),
	.rt	(instr[20:16]	),
	.rd	(instr[15:11]	),  // check !!!!
	.rd1	(rd1		),
	.rd2	(rd2		),
	.regwrite   (regwrite	)	
    );

    controller controller(
	.opcode	(instr[31:26]	),
	.funct	(instr[5:0]	),
	.rddst	(rddst		),
	.alusrc	(aluscr		),
	.memwrite   (memwrite	),
	.memread    (memread	),
	.jump	    (jump	),
	.branch	    (branch	),
	.regwrite   (regwrite	),
	.control    (control	)
    );

    alu alu(
	.control(control),
	.a	(rd1	),
	.b	(b	),  // check
	.result	(data	)
    );

    sing_ext ext(





endmodule


//CHECK AFTER!!!
module regfile(
    input regwrite,
    input [4:0] rs, rt, rd,
    input [31:0] writedata, // check
    output [31:0] rd1, rd2
);



endmodule
//CHECK AFTER!!!!


module controller(
    input [5:0] opcode, funct,
    output rddst, alusrc, memwrite, memread,
    output jump, branch, regwrite,
    output [2:0] control
);
    wire [1:0] aluop;

    dec dec(
	.opcode	(opcode		),
	.rddst	(rddst		),
	.alusrc	(aluscr		),
	.memwrite   (memwrite	),
	.memread    (memread	),
	.jump	    (jump	),
	.branch	    (branch	),
	.regwrite   (regwrite	),
	.aluop	    (aluop	)
    );

    aludec aludec(
	.funct	    (funct	),
	.aluop	    (aluop	),
	.control    (control	)
    );

endmodule

module dec(
    input [5:0] opcode,
    output rddst, alusrc, memwrite, memread,
    output jump, branch, regwrite,
    output [1:0] aluop
);

    reg [8:0] controls;

    always @* begin
	case(opcode)
	    6'h08 : controls = 9'b100000101;  // R type
	    6'h23: controls = 9'b010100100;  // lw
	    6'h2b: controls = 9'b011000000;  // sw
	    6'h04: controls = 9'b010001010;  // beq
	   // 6'h02: controls = 9'b01001010;  // jump
	endcase
    end

    assign {rddst, alusrc, memwrite, memread, jump, branch, regwrite, aluop} = controls;

endmodule

module aludec(
    input [1:0] aluop,
    input [5:0] funct,
    output [2:0] control
);

    reg [2:0] control;

    always @* begin
	case(aluop)
	    2'b00 : control = 3'b011;	// add (lw, sw)
	    2'b10 : control = 3'b111;	// sub (beq)
	    default : case(funct)
		6'h20 : control = 3'b011;   // add
		6'h22 : control = 3'b111;   // sub
		6'h24 : control = 3'b000;   // and
		6'h25 : control = 3'b001;   // or
		6'h2a : control = 3'b110;   // slt
	    endcase
	endcase
    end

endmodule

module alu(
    input [2:0] control,
    input [31:0] a,b,
    output [31:0] result
);

    wire [31:0] comple, sum;
    reg [31:0] result;

    assign comple = control[2] ? ~b : b;
    assign sum = a + comple + control[2];

    always @* begin
	case(control[1:0])
	    2'b11 : result = sum;
	    2'b00 : result = a & b;
	    2'b01 : result = a | b;
	    2'b10 : result = sum[31];
	endcase
    end	

    assign zero = (result == 32'b0);

endmodule

module sing_ext(
    input [15:0] offset,
    output [31:0] ext
);

    assign ext = offset[15] ? {16{offset[15],offset} : {0,offset};

endmodule

CPU_MIPS/tb.vcd
$date
	Sun Sep 06 18:55:04 2020
$end
$version
	Icarus Verilog
$end
$timescale
	10ps
$end
$scope module tb $end
$var wire 32 ! DATA [31:0] $end
$var reg 1 " CLK $end
$var reg 1 # RESET $end
$scope module top $end
$var wire 1 " clk $end
$var wire 1 # reset $end
$var wire 32 $ instr [31:0] $end
$var wire 32 % data [31:0] $end
$var wire 6 & addr [5:0] $end
$scope module imem $end
$var wire 32 ' instr [31:0] $end
$var wire 6 ( addr [5:0] $end
$upscope $end
$scope module mips $end
$var wire 1 ) aluscr $end
$var wire 32 * b [31:0] $end
$var wire 1 " clk $end
$var wire 32 + instr [31:0] $end
$var wire 32 , rd1 [31:0] $end
$var wire 32 - rd2 [31:0] $end
$var wire 1 # reset $end
$var wire 1 . regwrite $end
$var wire 1 / rddst $end
$var wire 1 0 memwrite $end
$var wire 1 1 memread $end
$var wire 1 2 jump $end
$var wire 32 3 data [31:0] $end
$var wire 3 4 control [2:0] $end
$var wire 1 5 branch $end
$var wire 6 6 addr [5:0] $end
$var reg 32 7 pc [31:0] $end
$scope module alu $end
$var wire 32 8 a [31:0] $end
$var wire 32 9 b [31:0] $end
$var wire 1 : zero $end
$var wire 32 ; sum [31:0] $end
$var wire 3 < control [2:0] $end
$var wire 32 = comple [31:0] $end
$var reg 32 > result [31:0] $end
$upscope $end
$scope module controller $end
$var wire 1 ) alusrc $end
$var wire 6 ? funct [5:0] $end
$var wire 6 @ opcode [5:0] $end
$var wire 1 . regwrite $end
$var wire 1 / rddst $end
$var wire 1 0 memwrite $end
$var wire 1 1 memread $end
$var wire 1 2 jump $end
$var wire 3 A control [2:0] $end
$var wire 1 5 branch $end
$var wire 1 B aluscr $end
$var wire 2 C aluop [1:0] $end
$scope module aludec $end
$var wire 6 D funct [5:0] $end
$var wire 2 E aluop [1:0] $end
$var reg 3 F control [2:0] $end
$upscope $end
$scope module dec $end
$var wire 6 G opcode [5:0] $end
$var wire 1 . regwrite $end
$var wire 1 / rddst $end
$var wire 1 0 memwrite $end
$var wire 1 1 memread $end
$var wire 1 2 jump $end
$var wire 1 5 branch $end
$var wire 1 B alusrc $end
$var wire 2 H aluop [1:0] $end
$var reg 9 I controls [8:0] $end
$upscope $end
$upscope $end
$scope module register $end
$var wire 5 J rd [4:0] $end
$var wire 32 K rd1 [31:0] $end
$var wire 32 L rd2 [31:0] $end
$var wire 1 . regwrite $end
$var wire 5 M rs [4:0] $end
$var wire 5 N rt [4:0] $end
$var wire 32 O writedata [31:0] $end
$upscope $end
$upscope $end
$upscope $end
$upscope $end
$enddefinitions $end
#0
$dumpvars
bz O
bx N
bx M
bz L
bz K
bx J
bx I
bx H
bx G
bx F
bx E
bx D
bx C
xB
bx A
bx @
bx ?
bx >
bz =
bx <
bx ;
x:
bz 9
bz 8
bx 7
bx 6
x5
bx 4
bx 3
x2
x1
x0
x/
x.
bz -
bz ,
bx +
bz *
z)
bx (
bx '
bx &
bx %
bx $
1#
0"
bx !
$end
#1000
1/
0B
00
01
02
05
1.
b1 C
b1 E
b1 H
b100000101 I
b0 M
b1 N
b0 J
b1000 @
b1000 G
b1011 ?
b1011 D
b100000000000010000000000001011 $
b100000000000010000000000001011 '
b100000000000010000000000001011 +
b0 &
b0 (
b0 6
b0 7
1"
#2000
0"
#3000
1"
#4000
0"
#5000
1"
#6000
0"
#7000
1"
#8000
0"
#9000
1"
#10000
0"
0#
#11000
bx M
bx N
bx J
bx @
bx G
bx ?
bx D
bx $
bx '
bx +
b100 &
b100 (
b100 6
b100 7
1"
#12000
0"
#13000
b1000 &
b1000 (
b1000 6
b1000 7
1"
#14000
0"
#15000
b1100 &
b1100 (
b1100 6
b1100 7
1"
#16000
0"
#17000
b10000 &
b10000 (
b10000 6
b10000 7
1"
#18000
0"
#19000
b10100 &
b10100 (
b10100 6
b10100 7
1"
#20000
0"
#21000
b11000 &
b11000 (
b11000 6
b11000 7
1"
#22000
0"
#23000
b11100 &
b11100 (
b11100 6
b11100 7
1"
#24000
0"
#25000
b100000 &
b100000 (
b100000 6
b100000 7
1"
#26000
0"
#27000
b100100 &
b100100 (
b100100 6
b100100 7
1"
#28000
0"
#29000
b101000 &
b101000 (
b101000 6
b101000 7
1"
#30000
0"
#31000
b101100 &
b101100 (
b101100 6
b101100 7
1"
#32000
0"
#33000
b110000 &
b110000 (
b110000 6
b110000 7
1"
#34000
0"
#35000
b110100 &
b110100 (
b110100 6
b110100 7
1"
#36000
0"
#37000
b111000 &
b111000 (
b111000 6
b111000 7
1"
#38000
0"
#39000
b111100 &
b111100 (
b111100 6
b111100 7
1"
#40000
0"
#41000
b0 M
b1 N
b0 J
b1000 @
b1000 G
b1011 ?
b1011 D
b100000000000010000000000001011 $
b100000000000010000000000001011 '
b100000000000010000000000001011 +
b0 &
b0 (
b0 6
b1000000 7
1"
#42000
0"
#43000
bx M
bx N
bx J
bx @
bx G
bx ?
bx D
bx $
bx '
bx +
b100 &
b100 (
b100 6
b1000100 7
1"
#44000
0"
#45000
b1000 &
b1000 (
b1000 6
b1001000 7
1"
#46000
0"
#47000
b1100 &
b1100 (
b1100 6
b1001100 7
1"
#48000
0"
#49000
b10000 &
b10000 (
b10000 6
b1010000 7
1"
#50000
0"
#51000
b10100 &
b10100 (
b10100 6
b1010100 7
1"
#52000
0"
#53000
b11000 &
b11000 (
b11000 6
b1011000 7
1"
#54000
0"
#55000
b11100 &
b11100 (
b11100 6
b1011100 7
1"
#56000
0"
#57000
b100000 &
b100000 (
b100000 6
b1100000 7
1"
#58000
0"
#59000
b100100 &
b100100 (
b100100 6
b1100100 7
1"
#60000
0"
#61000
b101000 &
b101000 (
b101000 6
b1101000 7
1"
#62000
0"
#63000
b101100 &
b101100 (
b101100 6
b1101100 7
1"
#64000
0"
#65000
b110000 &
b110000 (
b110000 6
b1110000 7
1"
#66000
0"
#67000
b110100 &
b110100 (
b110100 6
b1110100 7
1"
#68000
0"
#69000
b111000 &
b111000 (
b111000 6
b1111000 7
1"
#70000
0"
#71000
b111100 &
b111100 (
b111100 6
b1111100 7
1"
#72000
0"
#73000
b0 M
b1 N
b0 J
b1000 @
b1000 G
b1011 ?
b1011 D
b100000000000010000000000001011 $
b100000000000010000000000001011 '
b100000000000010000000000001011 +
b0 &
b0 (
b0 6
b10000000 7
1"
#74000
0"
#75000
bx M
bx N
bx J
bx @
bx G
bx ?
bx D
bx $
bx '
bx +
b100 &
b100 (
b100 6
b10000100 7
1"
#76000
0"
#77000
b1000 &
b1000 (
b1000 6
b10001000 7
1"
#78000
0"
#79000
b1100 &
b1100 (
b1100 6
b10001100 7
1"
#80000
0"
#81000
b10000 &
b10000 (
b10000 6
b10010000 7
1"
#82000
0"
#83000
b10100 &
b10100 (
b10100 6
b10010100 7
1"
#84000
0"
#85000
b11000 &
b11000 (
b11000 6
b10011000 7
1"
#86000
0"
#87000
b11100 &
b11100 (
b11100 6
b10011100 7
1"
#88000
0"
#89000
b100000 &
b100000 (
b100000 6
b10100000 7
1"
#90000
0"
#91000
b100100 &
b100100 (
b100100 6
b10100100 7
1"
#92000
0"
#93000
b101000 &
b101000 (
b101000 6
b10101000 7
1"
#94000
0"
#95000
b101100 &
b101100 (
b101100 6
b10101100 7
1"
#96000
0"
#97000
b110000 &
b110000 (
b110000 6
b10110000 7
1"
#98000
0"
#99000
b110100 &
b110100 (
b110100 6
b10110100 7
1"
#100000
0"
#101000
b111000 &
b111000 (
b111000 6
b10111000 7
1"
#102000
0"
#103000
b111100 &
b111100 (
b111100 6
b10111100 7
1"
#104000
0"
#105000
b0 M
b1 N
b0 J
b1000 @
b1000 G
b1011 ?
b1011 D
b100000000000010000000000001011 $
b100000000000010000000000001011 '
b100000000000010000000000001011 +
b0 &
b0 (
b0 6
b11000000 7
1"
#106000
0"
#107000
bx M
bx N
bx J
bx @
bx G
bx ?
bx D
bx $
bx '
bx +
b100 &
b100 (
b100 6
b11000100 7
1"
#108000
0"
#109000
b1000 &
b1000 (
b1000 6
b11001000 7
1"
#110000
0"
#111000
b1100 &
b1100 (
b1100 6
b11001100 7
1"
#112000
0"
#113000
b10000 &
b10000 (
b10000 6
b11010000 7
1"
#114000
0"
#115000
b10100 &
b10100 (
b10100 6
b11010100 7
1"
#116000
0"
#117000
b11000 &
b11000 (
b11000 6
b11011000 7
1"
#118000
0"
#119000
b11100 &
b11100 (
b11100 6
b11011100 7
1"
#120000
0"
#121000
b100000 &
b100000 (
b100000 6
b11100000 7
1"
#122000
0"
#123000
b100100 &
b100100 (
b100100 6
b11100100 7
1"
#124000
0"
#125000
b101000 &
b101000 (
b101000 6
b11101000 7
1"
#126000
0"
#127000
b101100 &
b101100 (
b101100 6
b11101100 7
1"
#128000
0"
#129000
b110000 &
b110000 (
b110000 6
b11110000 7
1"
#130000
0"
#131000
b110100 &
b110100 (
b110100 6
b11110100 7
1"
#132000
0"
#133000
b111000 &
b111000 (
b111000 6
b11111000 7
1"
#134000
0"
#135000
b111100 &
b111100 (
b111100 6
b11111100 7
1"
#136000
0"
#137000
b0 M
b1 N
b0 J
b1000 @
b1000 G
b1011 ?
b1011 D
b100000000000010000000000001011 $
b100000000000010000000000001011 '
b100000000000010000000000001011 +
b0 &
b0 (
b0 6
b100000000 7
1"
#138000
0"
#139000
bx M
bx N
bx J
bx @
bx G
bx ?
bx D
bx $
bx '
bx +
b100 &
b100 (
b100 6
b100000100 7
1"
#140000
0"
#141000
b1000 &
b1000 (
b1000 6
b100001000 7
1"
#142000
0"
#143000
b1100 &
b1100 (
b1100 6
b100001100 7
1"
#144000
0"
#145000
b10000 &
b10000 (
b10000 6
b100010000 7
1"
#146000
0"
#147000
b10100 &
b10100 (
b10100 6
b100010100 7
1"
#148000
0"
#149000
b11000 &
b11000 (
b11000 6
b100011000 7
1"
#150000
0"
#151000
b11100 &
b11100 (
b11100 6
b100011100 7
1"
#152000
0"
#153000
b100000 &
b100000 (
b100000 6
b100100000 7
1"
#154000
0"
#155000
b100100 &
b100100 (
b100100 6
b100100100 7
1"
#156000
0"
#157000
b101000 &
b101000 (
b101000 6
b100101000 7
1"
#158000
0"
#159000
b101100 &
b101100 (
b101100 6
b100101100 7
1"
#160000
0"
#161000
b110000 &
b110000 (
b110000 6
b100110000 7
1"
#162000
0"
#163000
b110100 &
b110100 (
b110100 6
b100110100 7
1"
#164000
0"
#165000
b111000 &
b111000 (
b111000 6
b100111000 7
1"
#166000
0"
#167000
b111100 &
b111100 (
b111100 6
b100111100 7
1"
#168000
0"
#169000
b0 M
b1 N
b0 J
b1000 @
b1000 G
b1011 ?
b1011 D
b100000000000010000000000001011 $
b100000000000010000000000001011 '
b100000000000010000000000001011 +
b0 &
b0 (
b0 6
b101000000 7
1"
#170000
0"
#171000
bx M
bx N
bx J
bx @
bx G
bx ?
bx D
bx $
bx '
bx +
b100 &
b100 (
b100 6
b101000100 7
1"
#172000
0"
#173000
b1000 &
b1000 (
b1000 6
b101001000 7
1"
#174000
0"
#175000
b1100 &
b1100 (
b1100 6
b101001100 7
1"
#176000
0"
#177000
b10000 &
b10000 (
b10000 6
b101010000 7
1"
#178000
0"
#179000
b10100 &
b10100 (
b10100 6
b101010100 7
1"
#180000
0"
#181000
b11000 &
b11000 (
b11000 6
b101011000 7
1"
#182000
0"
#183000
b11100 &
b11100 (
b11100 6
b101011100 7
1"
#184000
0"
#185000
b100000 &
b100000 (
b100000 6
b101100000 7
1"
#186000
0"
#187000
b100100 &
b100100 (
b100100 6
b101100100 7
1"
#188000
0"
#189000
b101000 &
b101000 (
b101000 6
b101101000 7
1"
#190000
0"
#191000
b101100 &
b101100 (
b101100 6
b101101100 7
1"
#192000
0"
#193000
b110000 &
b110000 (
b110000 6
b101110000 7
1"
#194000
0"
#195000
b110100 &
b110100 (
b110100 6
b101110100 7
1"
#196000
0"
#197000
b111000 &
b111000 (
b111000 6
b101111000 7
1"
#198000
0"
#199000
b111100 &
b111100 (
b111100 6
b101111100 7
1"
#200000
0"
#201000
b0 M
b1 N
b0 J
b1000 @
b1000 G
b1011 ?
b1011 D
b100000000000010000000000001011 $
b100000000000010000000000001011 '
b100000000000010000000000001011 +
b0 &
b0 (
b0 6
b110000000 7
1"
#202000
0"
#203000
bx M
bx N
bx J
bx @
bx G
bx ?
bx D
bx $
bx '
bx +
b100 &
b100 (
b100 6
b110000100 7
1"
#204000
0"
#205000
b1000 &
b1000 (
b1000 6
b110001000 7
1"
#206000
0"
#207000
b1100 &
b1100 (
b1100 6
b110001100 7
1"
#208000
0"
#209000
b10000 &
b10000 (
b10000 6
b110010000 7
1"
#210000
0"
#211000
b10100 &
b10100 (
b10100 6
b110010100 7
1"
#212000
0"
#213000
b11000 &
b11000 (
b11000 6
b110011000 7
1"
#214000
0"
#215000
b11100 &
b11100 (
b11100 6
b110011100 7
1"
#216000
0"
#217000
b100000 &
b100000 (
b100000 6
b110100000 7
1"
#218000
0"
#219000
b100100 &
b100100 (
b100100 6
b110100100 7
1"
#220000
0"
#221000
b101000 &
b101000 (
b101000 6
b110101000 7
1"
#222000
0"
#223000
b101100 &
b101100 (
b101100 6
b110101100 7
1"
#224000
0"
#225000
b110000 &
b110000 (
b110000 6
b110110000 7
1"
#226000
0"
#227000
b110100 &
b110100 (
b110100 6
b110110100 7
1"
#228000
0"
#229000
b111000 &
b111000 (
b111000 6
b110111000 7
1"
#230000
0"
#231000
b111100 &
b111100 (
b111100 6
b110111100 7
1"
#232000
0"
#233000
b0 M
b1 N
b0 J
b1000 @
b1000 G
b1011 ?
b1011 D
b100000000000010000000000001011 $
b100000000000010000000000001011 '
b100000000000010000000000001011 +
b0 &
b0 (
b0 6
b111000000 7
1"
#234000
0"
#235000
bx M
bx N
bx J
bx @
bx G
bx ?
bx D
bx $
bx '
bx +
b100 &
b100 (
b100 6
b111000100 7
1"
#236000
0"
#237000
b1000 &
b1000 (
b1000 6
b111001000 7
1"
#238000
0"
#239000
b1100 &
b1100 (
b1100 6
b111001100 7
1"
#240000
0"
#241000
b10000 &
b10000 (
b10000 6
b111010000 7
1"
#242000
0"
#243000
b10100 &
b10100 (
b10100 6
b111010100 7
1"
#244000
0"
#245000
b11000 &
b11000 (
b11000 6
b111011000 7
1"
#246000
0"
#247000
b11100 &
b11100 (
b11100 6
b111011100 7
1"
#248000
0"
#249000
b100000 &
b100000 (
b100000 6
b111100000 7
1"
#250000
0"
#251000
b100100 &
b100100 (
b100100 6
b111100100 7
1"
#252000
0"
#253000
b101000 &
b101000 (
b101000 6
b111101000 7
1"
#254000
0"
#255000
b101100 &
b101100 (
b101100 6
b111101100 7
1"
#256000
0"
#257000
b110000 &
b110000 (
b110000 6
b111110000 7
1"
#258000
0"
#259000
b110100 &
b110100 (
b110100 6
b111110100 7
1"
#260000
0"
#261000
b111000 &
b111000 (
b111000 6
b111111000 7
1"
#262000
0"
#263000
b111100 &
b111100 (
b111100 6
b111111100 7
1"
#264000
0"
#265000
b0 M
b1 N
b0 J
b1000 @
b1000 G
b1011 ?
b1011 D
b100000000000010000000000001011 $
b100000000000010000000000001011 '
b100000000000010000000000001011 +
b0 &
b0 (
b0 6
b1000000000 7
1"
#266000
0"
#267000
bx M
bx N
bx J
bx @
bx G
bx ?
bx D
bx $
bx '
bx +
b100 &
b100 (
b100 6
b1000000100 7
1"
#268000
0"
#269000
b1000 &
b1000 (
b1000 6
b1000001000 7
1"
#270000
0"
#271000
b1100 &
b1100 (
b1100 6
b1000001100 7
1"
#272000
0"
#273000
b10000 &
b10000 (
b10000 6
b1000010000 7
1"
#274000
0"
#275000
b10100 &
b10100 (
b10100 6
b1000010100 7
1"
#276000
0"
#277000
b11000 &
b11000 (
b11000 6
b1000011000 7
1"
#278000
0"
#279000
b11100 &
b11100 (
b11100 6
b1000011100 7
1"
#280000
0"
#281000
b100000 &
b100000 (
b100000 6
b1000100000 7
1"
#282000
0"
#283000
b100100 &
b100100 (
b100100 6
b1000100100 7
1"
#284000
0"
#285000
b101000 &
b101000 (
b101000 6
b1000101000 7
1"
#286000
0"
#287000
b101100 &
b101100 (
b101100 6
b1000101100 7
1"
#288000
0"
#289000
b110000 &
b110000 (
b110000 6
b1000110000 7
1"
#290000
0"
#291000
b110100 &
b110100 (
b110100 6
b1000110100 7
1"
#292000
0"
#293000
b111000 &
b111000 (
b111000 6
b1000111000 7
1"
#294000
0"
#295000
b111100 &
b111100 (
b111100 6
b1000111100 7
1"
#296000
0"
#297000
b0 M
b1 N
b0 J
b1000 @
b1000 G
b1011 ?
b1011 D
b100000000000010000000000001011 $
b100000000000010000000000001011 '
b100000000000010000000000001011 +
b0 &
b0 (
b0 6
b1001000000 7
1"
#298000
0"
#299000
bx M
bx N
bx J
bx @
bx G
bx ?
bx D
bx $
bx '
bx +
b100 &
b100 (
b100 6
b1001000100 7
1"
#300000
0"
#301000
b1000 &
b1000 (
b1000 6
b1001001000 7
1"
#302000
0"
#303000
b1100 &
b1100 (
b1100 6
b1001001100 7
1"
#304000
0"
#305000
b10000 &
b10000 (
b10000 6
b1001010000 7
1"
#306000
0"
#307000
b10100 &
b10100 (
b10100 6
b1001010100 7
1"
#308000
0"
#309000
b11000 &
b11000 (
b11000 6
b1001011000 7
1"
#310000
0"
#311000
b11100 &
b11100 (
b11100 6
b1001011100 7
1"
#312000
0"
#313000
b100000 &
b100000 (
b100000 6
b1001100000 7
1"
#314000
0"
#315000
b100100 &
b100100 (
b100100 6
b1001100100 7
1"
#316000
0"
#317000
b101000 &
b101000 (
b101000 6
b1001101000 7
1"
#318000
0"
#319000
b101100 &
b101100 (
b101100 6
b1001101100 7
1"
#320000
0"
#321000
b110000 &
b110000 (
b110000 6
b1001110000 7
1"
#322000
0"
#323000
b110100 &
b110100 (
b110100 6
b1001110100 7
1"
#324000
0"
#325000
b111000 &
b111000 (
b111000 6
b1001111000 7
1"
#326000
0"
#327000
b111100 &
b111100 (
b111100 6
b1001111100 7
1"
#328000
0"
#329000
b0 M
b1 N
b0 J
b1000 @
b1000 G
b1011 ?
b1011 D
b100000000000010000000000001011 $
b100000000000010000000000001011 '
b100000000000010000000000001011 +
b0 &
b0 (
b0 6
b1010000000 7
1"
#330000
0"
#331000
bx M
bx N
bx J
bx @
bx G
bx ?
bx D
bx $
bx '
bx +
b100 &
b100 (
b100 6
b1010000100 7
1"
#332000
0"
#333000
b1000 &
b1000 (
b1000 6
b1010001000 7
1"
#334000
0"
#335000
b1100 &
b1100 (
b1100 6
b1010001100 7
1"
#336000
0"
#337000
b10000 &
b10000 (
b10000 6
b1010010000 7
1"
#338000
0"
#339000
b10100 &
b10100 (
b10100 6
b1010010100 7
1"
#340000
0"
#341000
b11000 &
b11000 (
b11000 6
b1010011000 7
1"
#342000
0"
#343000
b11100 &
b11100 (
b11100 6
b1010011100 7
1"
#344000
0"
#345000
b100000 &
b100000 (
b100000 6
b1010100000 7
1"
#346000
0"
#347000
b100100 &
b100100 (
b100100 6
b1010100100 7
1"
#348000
0"
#349000
b101000 &
b101000 (
b101000 6
b1010101000 7
1"
#350000
0"
#351000
b101100 &
b101100 (
b101100 6
b1010101100 7
1"
#352000
0"
#353000
b110000 &
b110000 (
b110000 6
b1010110000 7
1"
#354000
0"
#355000
b110100 &
b110100 (
b110100 6
b1010110100 7
1"
#356000
0"
#357000
b111000 &
b111000 (
b111000 6
b1010111000 7
1"
#358000
0"
#359000
b111100 &
b111100 (
b111100 6
b1010111100 7
1"
#360000
0"
#361000
b0 M
b1 N
b0 J
b1000 @
b1000 G
b1011 ?
b1011 D
b100000000000010000000000001011 $
b100000000000010000000000001011 '
b100000000000010000000000001011 +
b0 &
b0 (
b0 6
b1011000000 7
1"
#362000
0"
#363000
bx M
bx N
bx J
bx @
bx G
bx ?
bx D
bx $
bx '
bx +
b100 &
b100 (
b100 6
b1011000100 7
1"
#364000
0"
#365000
b1000 &
b1000 (
b1000 6
b1011001000 7
1"
#366000
0"
#367000
b1100 &
b1100 (
b1100 6
b1011001100 7
1"
#368000
0"
#369000
b10000 &
b10000 (
b10000 6
b1011010000 7
1"
#370000
0"
#371000
b10100 &
b10100 (
b10100 6
b1011010100 7
1"
#372000
0"
#373000
b11000 &
b11000 (
b11000 6
b1011011000 7
1"
#374000
0"
#375000
b11100 &
b11100 (
b11100 6
b1011011100 7
1"
#376000
0"
#377000
b100000 &
b100000 (
b100000 6
b1011100000 7
1"
#378000
0"
#379000
b100100 &
b100100 (
b100100 6
b1011100100 7
1"
#380000
0"
#381000
b101000 &
b101000 (
b101000 6
b1011101000 7
1"
#382000
0"
#383000
b101100 &
b101100 (
b101100 6
b1011101100 7
1"
#384000
0"
#385000
b110000 &
b110000 (
b110000 6
b1011110000 7
1"
#386000
0"
#387000
b110100 &
b110100 (
b110100 6
b1011110100 7
1"
#388000
0"
#389000
b111000 &
b111000 (
b111000 6
b1011111000 7
1"
#390000
0"
#391000
b111100 &
b111100 (
b111100 6
b1011111100 7
1"
#392000
0"
#393000
b0 M
b1 N
b0 J
b1000 @
b1000 G
b1011 ?
b1011 D
b100000000000010000000000001011 $
b100000000000010000000000001011 '
b100000000000010000000000001011 +
b0 &
b0 (
b0 6
b1100000000 7
1"
#394000
0"
#395000
bx M
bx N
bx J
bx @
bx G
bx ?
bx D
bx $
bx '
bx +
b100 &
b100 (
b100 6
b1100000100 7
1"
#396000
0"
#397000
b1000 &
b1000 (
b1000 6
b1100001000 7
1"
#398000
0"
#399000
b1100 &
b1100 (
b1100 6
b1100001100 7
1"
#400000
0"
#401000
b10000 &
b10000 (
b10000 6
b1100010000 7
1"
#402000
0"
#403000
b10100 &
b10100 (
b10100 6
b1100010100 7
1"
#404000
0"
#405000
b11000 &
b11000 (
b11000 6
b1100011000 7
1"
#406000
0"
#407000
b11100 &
b11100 (
b11100 6
b1100011100 7
1"
#408000
0"
#409000
b100000 &
b100000 (
b100000 6
b1100100000 7
1"
#410000
0"
#411000
b100100 &
b100100 (
b100100 6
b1100100100 7
1"
#412000
0"
#413000
b101000 &
b101000 (
b101000 6
b1100101000 7
1"
#414000
0"
#415000
b101100 &
b101100 (
b101100 6
b1100101100 7
1"
#416000
0"
#417000
b110000 &
b110000 (
b110000 6
b1100110000 7
1"
#418000
0"
#419000
b110100 &
b110100 (
b110100 6
b1100110100 7
1"
#420000
0"
#421000
b111000 &
b111000 (
b111000 6
b1100111000 7
1"
#422000
0"
#423000
b111100 &
b111100 (
b111100 6
b1100111100 7
1"
#424000
0"
#425000
b0 M
b1 N
b0 J
b1000 @
b1000 G
b1011 ?
b1011 D
b100000000000010000000000001011 $
b100000000000010000000000001011 '
b100000000000010000000000001011 +
b0 &
b0 (
b0 6
b1101000000 7
1"
#426000
0"
#427000
bx M
bx N
bx J
bx @
bx G
bx ?
bx D
bx $
bx '
bx +
b100 &
b100 (
b100 6
b1101000100 7
1"
#428000
0"
#429000
b1000 &
b1000 (
b1000 6
b1101001000 7
1"
#430000
0"
#431000
b1100 &
b1100 (
b1100 6
b1101001100 7
1"
#432000
0"
#433000
b10000 &
b10000 (
b10000 6
b1101010000 7
1"
#434000
0"
#435000
b10100 &
b10100 (
b10100 6
b1101010100 7
1"
#436000
0"
#437000
b11000 &
b11000 (
b11000 6
b1101011000 7
1"
#438000
0"
#439000
b11100 &
b11100 (
b11100 6
b1101011100 7
1"
#440000
0"
#441000
b100000 &
b100000 (
b100000 6
b1101100000 7
1"
#442000
0"
#443000
b100100 &
b100100 (
b100100 6
b1101100100 7
1"
#444000
0"
#445000
b101000 &
b101000 (
b101000 6
b1101101000 7
1"
#446000
0"
#447000
b101100 &
b101100 (
b101100 6
b1101101100 7
1"
#448000
0"
#449000
b110000 &
b110000 (
b110000 6
b1101110000 7
1"
#450000
0"
#451000
b110100 &
b110100 (
b110100 6
b1101110100 7
1"
#452000
0"
#453000
b111000 &
b111000 (
b111000 6
b1101111000 7
1"
#454000
0"
#455000
b111100 &
b111100 (
b111100 6
b1101111100 7
1"
#456000
0"
#457000
b0 M
b1 N
b0 J
b1000 @
b1000 G
b1011 ?
b1011 D
b100000000000010000000000001011 $
b100000000000010000000000001011 '
b100000000000010000000000001011 +
b0 &
b0 (
b0 6
b1110000000 7
1"
#458000
0"
#459000
bx M
bx N
bx J
bx @
bx G
bx ?
bx D
bx $
bx '
bx +
b100 &
b100 (
b100 6
b1110000100 7
1"
#460000
0"
#461000
b1000 &
b1000 (
b1000 6
b1110001000 7
1"
#462000
0"
#463000
b1100 &
b1100 (
b1100 6
b1110001100 7
1"
#464000
0"
#465000
b10000 &
b10000 (
b10000 6
b1110010000 7
1"
#466000
0"
#467000
b10100 &
b10100 (
b10100 6
b1110010100 7
1"
#468000
0"
#469000
b11000 &
b11000 (
b11000 6
b1110011000 7
1"
#470000
0"
#471000
b11100 &
b11100 (
b11100 6
b1110011100 7
1"
#472000
0"
#473000
b100000 &
b100000 (
b100000 6
b1110100000 7
1"
#474000
0"
#475000
b100100 &
b100100 (
b100100 6
b1110100100 7
1"
#476000
0"
#477000
b101000 &
b101000 (
b101000 6
b1110101000 7
1"
#478000
0"
#479000
b101100 &
b101100 (
b101100 6
b1110101100 7
1"
#480000
0"
#481000
b110000 &
b110000 (
b110000 6
b1110110000 7
1"
#482000
0"
#483000
b110100 &
b110100 (
b110100 6
b1110110100 7
1"
#484000
0"
#485000
b111000 &
b111000 (
b111000 6
b1110111000 7
1"
#486000
0"
#487000
b111100 &
b111100 (
b111100 6
b1110111100 7
1"
#488000
0"
